notifelect/__init__.py
notifelect/__main__.py
notifelect/_version.py
notifelect/cli.py
notifelect/election_manager.py
notifelect/logconfig.py
notifelect/models.py
notifelect/py.typed
notifelect/queries.py
notifelect/tm.py
notifelect-0.0.3.dist-info/LICENSE
notifelect-0.0.3.dist-info/METADATA
notifelect-0.0.3.dist-info/WHEEL
notifelect-0.0.3.dist-info/top_level.txt
notifelect-0.0.3.dist-info/RECORD
