Metadata-Version: 2.1
Name: notifelect
Version: 0.0.3
Summary: A distributed leader election python package using postgresql notify.
Author: janbjorge
License: MIT License
Project-URL: Documentation, https://github.com/janbjorge/notifelect/wiki
Project-URL: Homepage, https://github.com/janbjorge/notifelect/
Project-URL: Issues, https://github.com/janbjorge/notifelect/issues
Project-URL: Repository, https://github.com/janbjorge/notifelect/
Classifier: Development Status :: 4 - Beta
Classifier: Environment :: Web Environment
Classifier: Framework :: AsyncIO
Classifier: Intended Audience :: Developers
Classifier: License :: OSI Approved :: MIT License
Classifier: Natural Language :: English
Classifier: Operating System :: OS Independent
Classifier: Programming Language :: Python :: 3.10
Classifier: Programming Language :: Python :: 3.11
Classifier: Programming Language :: Python :: 3.12
Classifier: Programming Language :: Python
Classifier: Topic :: Database
Classifier: Topic :: Software Development :: Libraries :: Python Modules
Classifier: Topic :: Utilities
Classifier: Topic :: System :: Distributed Computing
Requires-Python: >=3.10
License-File: LICENSE
Requires-Dist: asyncpg
Requires-Dist: pydantic >=2.0.0
Provides-Extra: dev
Requires-Dist: asyncpg ; extra == 'dev'
Requires-Dist: asyncpg-stubs ; extra == 'dev'
Requires-Dist: mypy-extensions ; extra == 'dev'
Requires-Dist: mypy ; extra == 'dev'
Requires-Dist: pytest-asyncio ; extra == 'dev'
Requires-Dist: pytest ; extra == 'dev'
Requires-Dist: ruff ; extra == 'dev'
Provides-Extra: docs
Requires-Dist: myst-parser ; extra == 'docs'
Requires-Dist: sphinx ; extra == 'docs'
Requires-Dist: sphinx-rtd-theme ; extra == 'docs'
